barc_analytics/__init__.py
barc_analytics/analytics_script.py
barc_analytics-0.0.1.dist-info/LICENSE.txt
barc_analytics-0.0.1.dist-info/METADATA
barc_analytics-0.0.1.dist-info/WHEEL
barc_analytics-0.0.1.dist-info/entry_points.txt
barc_analytics-0.0.1.dist-info/top_level.txt
barc_analytics-0.0.1.dist-info/RECORD
