Metadata-Version: 2.1
Name: barc-analytics
Version: 0.0.1
Summary: Analytics scripts for BARC Network Traffic
Author: Rishaab Dhar
Author-email: Rishaab Dhar <rishaabdhar@gmail.com>
License: The MIT License (MIT)
Platform: any
Classifier: Development Status :: 4 - Beta
Classifier: Programming Language :: Python :: 3
Classifier: License :: OSI Approved :: MIT License
Classifier: Operating System :: OS Independent
Requires-Python: >=3.6
License-File: LICENSE.txt
